fpga/src/apb2_led.v
`ifndef __APB2_LED_V__
`define __APB2_LED_V__

/**
 * Simple module for driving a led via APB2 bus
 */
module apb2_led (
    pclk,
    preset_n,
    penable,
    pwrite,
    paddr,
    pwdata,
    pstrb,
    pprot,
    psel,
    prdata,
    pready,
    pslverr,
    led_state
);
  parameter data_width = 32;
  parameter addr_width = 8;
  parameter led_count = 1;
  localparam strobe_count = data_width / 8;

  input pclk, preset_n, penable, pwrite;
  input [addr_width - 1:0] paddr;
  input [data_width - 1:0] pwdata;
  input [strobe_count - 1:0] pstrb;
  input [2:0] pprot;

  input psel;

  output reg [data_width - 1:0] prdata;
  output reg pready;
  output reg pslverr;
  output reg [led_count - 1:0] led_state;

  localparam idle_state = 2'b00;
  localparam w_enable = 2'b01;
  localparam r_enable = 2'b10;

  reg [1:0] state_;

  always @(negedge preset_n or posedge pclk) begin
    if (preset_n == 0) begin
      state_ <= idle_state;
      prdata <= {data_width{1'bz}};
      pready <= 0;
      pslverr <= 0;
      led_state <= 0;
    end else begin
      case (state_)
        idle_state: begin
          prdata <= {data_width{1'bz}};
          pready <= 0;
          if (psel) begin
            if (pwrite) state_ <= w_enable;
            else state_ <= r_enable;
          end
        end
        w_enable: begin
          if (psel && pwrite) begin
            if (paddr == 0) begin
              led_state <= pwdata[led_count-1:0];
              pready <= 1;
            end else begin
              pslverr <= 1;
              pready  <= 1;
            end
          end
          state_ = idle_state;
        end
        r_enable: begin
          if (psel && !pwrite) begin
            if (paddr == 0) begin
              prdata <= led_state;
              pready <= 1;
            end else begin
              pslverr <= 1;
              pready  <= 1;
            end
          end
          state_ = idle_state;
        end
        default: begin
          state_ <= idle_state;
        end
      endcase
    end
  end


endmodule

`endif  // __APB2_LED_V__

src/apb2_led_tb.v
`include "apb2_led.v"

`timescale 1ns / 1ps

module apb2_led_tb;

  localparam data_width = 32;
  localparam addr_width = 8;
  localparam strobe_count = data_width / 8;
  localparam tick = 2;

  reg clk = 0, rst_n = 0, enable, write;

  reg [addr_width - 1:0] addr;
  reg [data_width - 1:0] wdata;
  reg [strobe_count - 1:0] strb = {strobe_count{1'b1}};
  reg [2:0] prot = 0;
  reg sel;

  wire [data_width - 1:0] rdata;
  wire ready;
  wire slverr;

  wire led_state;


  apb2_led led_ (
      .pclk(clk),
      .preset_n(rst_n),
      .penable(enable),
      .pwrite(write),
      .paddr(addr),
      .pwdata(wdata),
      .pstrb(strb),
      .pprot(prot),
      .psel(sel),
      .prdata(rdata),
      .pready(ready),
      .pslverr(slverr),
      .led_state(led_state)
  );

  always #1 clk = ~clk;

  initial begin
    $dumpfile("apb2_led_tb");
    $dumpvars(0, apb2_led_tb);

    write = 0;

    #tick;

    rst_n = 1;

    $display("Write value");
    // setup phase
    write = 1;
    addr  = 0;
    wdata = 'b1;
    sel   = 1;

    #tick;
    // access phase
    enable = 1;

    #tick;

    enable = 0;
    write = 0;
    sel = 0;

    #tick;

    $display("Read value");
    // setup phase
    write = 0;
    addr  = 0;
    sel   = 1;

    #tick;
    // access phase
    enable = 1;

    #tick;

    enable = 0;
    write = 0;
    sel = 0;

    #tick;

    $display("Write value");
    // setup phase
    write = 1;
    addr  = 0;
    wdata = 'b0;
    sel   = 1;

    #tick;
    // access phase
    enable = 1;

    #tick;

    enable = 0;
    write = 0;
    sel = 0;

    #tick;

    $finish;
  end


endmodule

src/apb2_led_tb.vcd
$date
	Thu Jun 29 13:20:00 2023
$end
$version
	Icarus Verilog
$end
$timescale
	1ps
$end
$scope module apb2_led_tb $end
$var wire 1 ! slverr $end
$var wire 1 " ready $end
$var wire 32 # rdata [31:0] $end
$var wire 1 $ led_state $end
$var parameter 32 % addr_width $end
$var parameter 32 & data_width $end
$var parameter 32 ' strobe_count $end
$var parameter 32 ( tick $end
$var reg 8 ) addr [7:0] $end
$var reg 1 * clk $end
$var reg 1 + enable $end
$var reg 3 , prot [2:0] $end
$var reg 1 - rst_n $end
$var reg 1 . sel $end
$var reg 4 / strb [3:0] $end
$var reg 32 0 wdata [31:0] $end
$var reg 1 1 write $end
$scope module led_ $end
$var wire 8 2 paddr [7:0] $end
$var wire 1 * pclk $end
$var wire 1 + penable $end
$var wire 3 3 pprot [2:0] $end
$var wire 1 - preset_n $end
$var wire 1 . psel $end
$var wire 4 4 pstrb [3:0] $end
$var wire 32 5 pwdata [31:0] $end
$var wire 1 1 pwrite $end
$var parameter 32 6 addr_width $end
$var parameter 32 7 data_width $end
$var parameter 2 8 idle_state $end
$var parameter 32 9 led_count $end
$var parameter 2 : r_enable $end
$var parameter 32 ; strobe_count $end
$var parameter 2 < w_enable $end
$var reg 1 $ led_state $end
$var reg 32 = prdata [31:0] $end
$var reg 1 " pready $end
$var reg 1 ! pslverr $end
$var reg 2 > state_ [1:0] $end
$upscope $end
$upscope $end
$enddefinitions $end
$comment Show the parameter values. $end
$dumpall
b1 <
b100 ;
b10 :
b1 9
b0 8
b100000 7
b1000 6
b10 (
b100 '
b100000 &
b1000 %
$end
#0
$dumpvars
b0 >
bz =
bx 5
b1111 4
b0 3
bx 2
01
bx 0
b1111 /
x.
0-
b0 ,
x+
0*
bx )
0$
bz #
0"
0!
$end
#1000
1*
#2000
0*
1.
b1 0
b1 5
b0 )
b0 2
11
1-
#3000
b1 >
1*
#4000
0*
1+
#5000
1"
1$
b0 >
1*
#6000
0*
0.
01
0+
#7000
0"
1*
#8000
0*
1.
#9000
b10 >
1*
#10000
0*
1+
#11000
1"
b1 #
b1 =
b0 >
1*
#12000
0*
0.
0+
#13000
0"
bz #
bz =
1*
#14000
0*
1.
b0 0
b0 5
11
#15000
b1 >
1*
#16000
0*
1+
#17000
1"
0$
b0 >
1*
#18000
0*
0.
01
0+
#19000
0"
1*
