src/dummy-ram.v
`ifndef __DUMMY_RAM_V__
`define __DUMMY_RAM_V__

module dummy_apb2_ram (
    clk,
    rst_n,
    enable,
    write,
    addr,
    wdata,
    strb,
    prot,
    sel,
    rdata,
    ready,
    slverr
);
  parameter data_width = 32;
  parameter addr_width = 8;

  localparam strobe_count = data_width / 8;

  input clk, rst_n, enable, write;
  input [addr_width - 1:0] addr;
  input [data_width - 1:0] wdata;
  input [strobe_count - 1:0] strb;
  input [2:0] prot;
  input sel;

  output reg [data_width - 1:0] rdata;
  output reg ready;
  output reg slverr;

  localparam idle_state = 2'b00;
  localparam w_enable = 2'b01;
  localparam r_enable = 2'b10;

  reg [data_width - 1:0] ram_[0:2**addr_width - 1];
  reg [1:0] state_;

  always @(negedge rst_n or posedge clk) begin
    if (rst_n == 0) begin
      state_ <= idle_state;
      rdata  <= {data_width{1'bx}};
      ready  <= 0;
      slverr <= 0;
    end else begin
      case (state_)
        idle_state: begin
          rdata <= {data_width{1'bx}};
          ready <= 0;
          if (sel) begin
            if (write) state_ <= w_enable;
            else state_ <= r_enable;
          end
        end
        w_enable: begin
          if (sel && write) begin
            ram_[addr] <= wdata;
            ready <= 1;
          end
          state_ = idle_state;
        end
        r_enable: begin
          if (sel && !write) begin
            rdata <= ram_[addr];
            ready <= 1;
          end
          state_ = idle_state;
        end
        default: begin
          state_ <= idle_state;
        end
      endcase
    end
  end

endmodule

`endif  // __DUMMY_RAM_V__

src/dummy_ram_tb.v
`include "dummy-ram.v"

`timescale 1ns / 1ps

module dummy_apb2_ram_tb;
  localparam data_width = 32;
  localparam addr_width = 8;
  localparam strobe_count = data_width / 8;
  localparam tick = 2;

  reg clk = 0, rst_n = 0, enable, write;

  reg [addr_width - 1:0] addr;
  reg [data_width - 1:0] wdata;
  reg [strobe_count - 1:0] strb = {strobe_count{1'b1}};
  reg [2:0] prot = 0;
  reg sel;

  wire [data_width - 1:0] rdata;
  wire ready;
  wire slverr;


  always #1 clk = ~clk;

  dummy_apb2_ram ram_ (
      .clk(clk),
      .rst_n(rst_n),
      .enable(enable),
      .write(write),
      .addr(addr),
      .wdata(wdata),
      .strb(strb),
      .prot(prot),
      .sel(sel),
      .rdata(rdata),
      .ready(ready),
      .slverr(slverr)
  );

  initial begin
    $dumpfile("dummy_apb2_ram_tb");
    $dumpvars(0, dummy_apb2_ram_tb);

    write = 0;

    #tick;

    rst_n = 1;

    $display("Write value");
    // setup phase
    write = 1;
    addr  = 'd13;
    wdata = 'd42;
    sel   = 1;

    #tick;
    // access phase
    enable = 1;

    #tick;

    enable = 0;
    write = 0;
    sel = 0;

    #tick;

    $display("Read value");
    // setup phase
    write = 0;
    addr  = 'd13;
    sel   = 1;

    #tick;
    // access phase
    enable = 1;

    #tick;

    enable = 0;
    write = 0;
    sel = 0;

    #tick;

    $finish;
  end

endmodule

src/dummy_apb2_ram_tb.vcd
$date
	Fri Jun 23 11:27:51 2023
$end
$version
	Icarus Verilog
$end
$timescale
	1ps
$end
$scope module dummy_apb2_ram_tb $end
$var wire 1 ! slverr $end
$var wire 1 " ready $end
$var wire 32 # rdata [31:0] $end
$var parameter 32 $ addr_width $end
$var parameter 32 % data_width $end
$var parameter 32 & strobe_count $end
$var parameter 32 ' tick $end
$var reg 8 ( addr [7:0] $end
$var reg 1 ) clk $end
$var reg 1 * enable $end
$var reg 3 + prot [2:0] $end
$var reg 1 , rst_n $end
$var reg 1 - sel $end
$var reg 4 . strb [3:0] $end
$var reg 32 / wdata [31:0] $end
$var reg 1 0 write $end
$scope module ram_ $end
$var wire 8 1 addr [7:0] $end
$var wire 1 ) clk $end
$var wire 1 * enable $end
$var wire 3 2 prot [2:0] $end
$var wire 1 , rst_n $end
$var wire 1 - sel $end
$var wire 4 3 strb [3:0] $end
$var wire 32 4 wdata [31:0] $end
$var wire 1 0 write $end
$var parameter 32 5 addr_width $end
$var parameter 32 6 data_width $end
$var parameter 2 7 idle_state $end
$var parameter 2 8 r_enable $end
$var parameter 32 9 strobe_count $end
$var parameter 2 : w_enable $end
$var reg 32 ; rdata [31:0] $end
$var reg 1 " ready $end
$var reg 1 ! slverr $end
$var reg 2 < state_ [1:0] $end
$upscope $end
$upscope $end
$enddefinitions $end
$comment Show the parameter values. $end
$dumpall
b1 :
b100 9
b10 8
b0 7
b100000 6
b1000 5
b10 '
b100 &
b100000 %
b1000 $
$end
#0
$dumpvars
b0 <
bx ;
bx 4
b1111 3
b0 2
bx 1
00
bx /
b1111 .
x-
0,
b0 +
x*
0)
bx (
bx #
0"
0!
$end
#1000
1)
#2000
0)
1-
b101010 /
b101010 4
b1101 (
b1101 1
10
1,
#3000
b1 <
1)
#4000
0)
1*
#5000
1"
b0 <
1)
#6000
0)
0-
00
0*
#7000
0"
1)
#8000
0)
1-
#9000
b10 <
1)
#10000
0)
1*
#11000
1"
b101010 #
b101010 ;
b0 <
1)
#12000
0)
0-
0*
#13000
0"
bx #
bx ;
1)
